[
    {
        "Товар": "Телефон Apple iPhone 15 128GB (черный)",
        "Цена": "от 2180,00 р.",
        "Рейтинг": "4,4"
    },
    {
        "Товар": "Телефон Apple iPhone 16 Pro 256GB (пустынный титан)",
        "Цена": "от 3700,00 р.",
        "Рейтинг": "4,5"
    },
    {
        "Товар": "Телефон Apple iPhone 16 128GB (ультрамарин)",
        "Цена": "от 2579,00 р.",
        "Рейтинг": "4,9"
    },
    {
        "Товар": "Телефон Apple iPhone 16e 128GB (черный)",
        "Цена": "от 2041,86 р.",
        "Рейтинг": "4,8"
    },
    {
        "Товар": "Телефон Apple iPhone 16 128GB (черный)",
        "Цена": "от 2450,00 р.",
        "Рейтинг": "4,9"
    },
    {
        "Товар": "Телефон Apple iPhone 15 Pro 256GB (природный титан)",
        "Цена": "от 3550,00 р.",
        "Рейтинг": "4,4"
    },
    {
        "Товар": "Наушники Xiaomi Buds 5 M2341E1 (графитовый черный, международная версия)",
        "Цена": "от 341,62 р.",
        "Рейтинг": "4,9"
    },
    {
        "Товар": "Наушники SteelSeries Arctis 7+ Wireless (черный)",
        "Цена": "Наушники HyperX Cloud Core Wireless",
        "Рейтинг": "3"
    },
    {
        "Товар": "Наушники Havit H655BT Pro (синий)",
        "Цена": "от 88,00 р.",
        "Рейтинг": "5"
    },
    {
        "Товар": "Наушники JBL Live Flex (черный)",
        "Цена": "от 439,00 р.",
        "Рейтинг": "3,3"
    },
    {
        "Товар": "Газонокосилка Villartec ME 1233",
        "Цена": "от 330,00 р.",
        "Рейтинг": "5"
    },
    {
        "Товар": "Газонокосилка GPT GLM-T4629SA",
        "Цена": "от 999,00 р.",
        "Рейтинг": "5"
    },
    {
        "Товар": "Газонокосилка GPT GLM-Т5642ST-H",
        "Цена": "от 2520,00 р.",
        "Рейтинг": "5"
    },
    {
        "Товар": "SSD ADATA Legend 900 1TB SLEG-900-1TCS",
        "Цена": "от 234,00 р.",
        "Рейтинг": "3,7"
    },
    {
        "Товар": "SSD ADATA XPG GAMMIX S70 Blade 1TB AGAMMIXS70B-1T-CS",
        "Цена": "от 274,10 р.",
        "Рейтинг": "4,3"
    },
    {
        "Товар": "SSD Apacer AS2280P4 512GB AP512GAS2280P4-1",
        "Цена": "от 108,29 р.",
        "Рейтинг": "4,7"
    },
    {
        "Товар": "SSD Apacer AS350X 1TB AP1TBAS350XR-1",
        "Цена": "от 192,94 р.",
        "Рейтинг": "4,7"
    },
    {
        "Товар": "от 182,47 р.",
        "Цена": "SSD Team MP44Q 1TB TM8FFD001T0C101",
        "Рейтинг": "5"
    },
    {
        "Товар": "Видеокарта Palit GeForce RTX 4070 Super Dual OC 12GB NED407SS19K9-1043D",
        "Цена": "от 3279,00 р.",
        "Рейтинг": "4,4"
    },
    {
        "Товар": "Видеокарта Palit GeForce RTX 5060 Dual NE75060019P1-GB2063D",
        "Цена": "от 1695,98 р.",
        "Рейтинг": "4,5"
    },
    {
        "Товар": "от 2928,31 р.",
        "Цена": "Видеокарта Gigabyte GeForce RTX 5070 Windforce OC SFF 12G GV-N5070WF3OC-12GD",
        "Рейтинг": "5"
    },
    {
        "Товар": "от 2098,34 р.",
        "Цена": "Видеокарта Gigabyte GeForce RTX 5070 Aero OC 12G GV-N5070AERO OC-12GD",
        "Рейтинг": "4,7"
    },
    {
        "Товар": "Триммер Villartec CB 242B",
        "Цена": "от 425,00 р.",
        "Рейтинг": "5"
    },
    {
        "Товар": "Триммер Greenworks G24ST25K2 2107207SA (с 1-им АКБ)",
        "Цена": "от 325,00 р.",
        "Рейтинг": "4,3"
    },
    {
        "Товар": "Триммер ECO GTP-215 Power",
        "Цена": "от 301,80 р.",
        "Рейтинг": "5"
    },
    {
        "Товар": "Триммер Hyundai GC 1405",
        "Цена": "от 377,50 р.",
        "Рейтинг": "4,4"
    },
    {
        "Товар": "Триммер ELAND GTR-250",
        "Цена": "от 434,60 р.",
        "Рейтинг": "3,7"
    },
    {
        "Товар": "Ноутбук ASUS Vivobook 15 X1504ZA-BQ1120",
        "Цена": "Игровой ноутбук Lenovo LOQ 15IAX9 83GS00EMRK",
        "Рейтинг": "4,8"
    },
    {
        "Товар": "Игровой ноутбук Lenovo IdeaPad Gaming 3 16IAH7 82SA00CXRK",
        "Цена": "Игровой ноутбук HP Victus 15-fb2063dx 9Z7L4UA + 8 ГБ MTC4C10163S1SC56BD1",
        "Рейтинг": "4,3"
    },
    {
        "Товар": "Ноутбук Chuwi GemiBook XPro CWI574-iN10008G256G",
        "Цена": "от 947,75 р.",
        "Рейтинг": "5"
    },
    {
        "Товар": "Ноутбук Chuwi HeroBook Pro CWI514-iN40208G256G",
        "Цена": "от 705,60 р.",
        "Рейтинг": "4,8"
    },
    {
        "Товар": "Телевизор Xiaomi TV A 55\" 2025 (международная версия)",
        "Цена": "от 1364,83 р.",
        "Рейтинг": "4,5"
    },
    {
        "Товар": "Телевизор LG UT81 50UT81006LA",
        "Цена": "от 1705,00 р.",
        "Рейтинг": "3,7"
    },
    {
        "Товар": "Телевизор Xiaomi TV A Pro 43\" 2025 (международная версия)",
        "Цена": "от 1007,00 р.",
        "Рейтинг": "3,9"
    },
    {
        "Товар": "Телевизор iFFALCON 43U65",
        "Цена": "от 899,00 р.",
        "Рейтинг": "4,7"
    },
    {
        "Товар": "Телевизор Samsung Crystal UHD DU7100 UE43DU7100UXRU",
        "Цена": "от 1174,00 р.",
        "Рейтинг": "4"
    },
    {
        "Товар": "Холодильник LG DoorCooling+ GC-B509FTZW",
        "Цена": "от 3199,00 р.",
        "Рейтинг": "3,8"
    },
    {
        "Товар": "Холодильник ATLANT ХМ 4621-101 NL",
        "Цена": "от 1430,00 р.",
        "Рейтинг": "5"
    },
    {
        "Товар": "Холодильник ATLANT ХМ-4319-101",
        "Цена": "от 1328,68 р.",
        "Рейтинг": "4,7"
    },
    {
        "Товар": "Холодильник ATLANT ХМ 4626-109 ND",
        "Цена": "от 1609,00 р.",
        "Рейтинг": "4,2"
    },
    {
        "Товар": "от 894,00 р.",
        "Цена": "Холодильник LG DoorCooling+ GC-B459SLCL",
        "Рейтинг": "4,4"
    },
    {
        "Товар": "Процессор AMD Ryzen 5 7500F",
        "Цена": "от 449,98 р.",
        "Рейтинг": "4,8"
    },
    {
        "Товар": "Процессор AMD Ryzen 7 7800X3D",
        "Цена": "от 1329,67 р.",
        "Рейтинг": "4,9"
    },
    {
        "Товар": "Процессор AMD Ryzen 5 5600",
        "Цена": "от 269,98 р.",
        "Рейтинг": "5"
    },
    {
        "Товар": "Процессор AMD Ryzen 7 7700",
        "Цена": "от 698,46 р.",
        "Рейтинг": "4,9"
    },
    {
        "Товар": "Процессор AMD Ryzen 7 5700X",
        "Цена": "от 401,63 р.",
        "Рейтинг": "5"
    },
    {
        "Товар": "Процессор Intel Core i5-12400F",
        "Цена": "от 311,45 р.",
        "Рейтинг": "5"
    }
]